readarr/__init__.py
readarr/api_client.py
readarr/api_response.py
readarr/configuration.py
readarr/exceptions.py
readarr/py.typed
readarr/rest.py
readarr/api/__init__.py
readarr/api/api_info_api.py
readarr/api/authentication_api.py
readarr/api/author_api.py
readarr/api/author_editor_api.py
readarr/api/author_lookup_api.py
readarr/api/backup_api.py
readarr/api/blocklist_api.py
readarr/api/book_api.py
readarr/api/book_editor_api.py
readarr/api/book_file_api.py
readarr/api/book_lookup_api.py
readarr/api/bookshelf_api.py
readarr/api/calendar_api.py
readarr/api/calendar_feed_api.py
readarr/api/command_api.py
readarr/api/custom_filter_api.py
readarr/api/custom_format_api.py
readarr/api/cutoff_api.py
readarr/api/delay_profile_api.py
readarr/api/development_config_api.py
readarr/api/disk_space_api.py
readarr/api/download_client_api.py
readarr/api/download_client_config_api.py
readarr/api/edition_api.py
readarr/api/file_system_api.py
readarr/api/health_api.py
readarr/api/history_api.py
readarr/api/host_config_api.py
readarr/api/import_list_api.py
readarr/api/import_list_exclusion_api.py
readarr/api/indexer_api.py
readarr/api/indexer_config_api.py
readarr/api/language_api.py
readarr/api/localization_api.py
readarr/api/log_api.py
readarr/api/log_file_api.py
readarr/api/manual_import_api.py
readarr/api/media_cover_api.py
readarr/api/media_management_config_api.py
readarr/api/metadata_api.py
readarr/api/metadata_profile_api.py
readarr/api/metadata_profile_schema_api.py
readarr/api/metadata_provider_config_api.py
readarr/api/missing_api.py
readarr/api/naming_config_api.py
readarr/api/notification_api.py
readarr/api/parse_api.py
readarr/api/ping_api.py
readarr/api/quality_definition_api.py
readarr/api/quality_profile_api.py
readarr/api/quality_profile_schema_api.py
readarr/api/queue_action_api.py
readarr/api/queue_api.py
readarr/api/queue_details_api.py
readarr/api/queue_status_api.py
readarr/api/release_api.py
readarr/api/release_profile_api.py
readarr/api/release_push_api.py
readarr_py-1.1.0.dist-info/LICENSE
readarr_py-1.1.0.dist-info/METADATA
readarr_py-1.1.0.dist-info/WHEEL
readarr_py-1.1.0.dist-info/top_level.txt
readarr_py-1.1.0.dist-info/RECORD
